websocket_notifications/__init__.py
websocket_notifications/admin.py
websocket_notifications/api/__init__.py
websocket_notifications/api/rest_framework.py
websocket_notifications/apps.py
websocket_notifications/consumers.py
websocket_notifications/helpers.py
websocket_notifications/managers.py
websocket_notifications/migrations/0001_initial.py
websocket_notifications/migrations/0002_alter_notificationgroup_id.py
websocket_notifications/migrations/__init__.py
websocket_notifications/models.py
websocket_notifications/routing.py
websocket_notifications/settings.py
websocket_notifications/snitch/__init__.py
websocket_notifications/snitch/backends.py
websocket_notifications/templates/websocket_notifications/listener.html
websocket_notifications/urls.py
websocket_notifications/views.py
django_websocket_notifications-1.3.1.dist-info/LICENSE
django_websocket_notifications-1.3.1.dist-info/METADATA
django_websocket_notifications-1.3.1.dist-info/WHEEL
django_websocket_notifications-1.3.1.dist-info/RECORD
