Metadata-Version: 2.1
Name: django-websocket-notifications
Version: 1.3.1
Summary: A Django package to handle notifications using Django Channels and WebSockets.
Home-page: https://github.com/marcosgabarda/django-websocket-notifications
License: MIT
Author: Marcos Gabarda
Author-email: hey@marcosgabarda.com
Requires-Python: >=3.8,<4.0
Classifier: Environment :: Web Environment
Classifier: Framework :: Django
Classifier: License :: OSI Approved :: MIT License
Classifier: Programming Language :: Python :: 3
Classifier: Programming Language :: Python :: 3.8
Classifier: Programming Language :: Python :: 3.9
Classifier: Programming Language :: Python :: 3.10
Classifier: Programming Language :: Python :: 3.11
Requires-Dist: channels (>=2.4.0)
Requires-Dist: django (>=4.0.0)
Requires-Dist: django-model-utils (>=4.0.0)
Requires-Dist: django-snitch (>=2.1.0)
Requires-Dist: djangorestframework (>=3.11.0)
Requires-Dist: single-source (>=0.3.0,<0.4.0)
